anshudi/__init__.py
anshudi/anshu.py
anshudi-2.0.0.dist-info/METADATA
anshudi-2.0.0.dist-info/WHEEL
anshudi-2.0.0.dist-info/top_level.txt
anshudi-2.0.0.dist-info/RECORD
