Metadata-Version: 2.1
Name: anshudi
Version: 2.0.0
Summary: A Python package
Author: Your Name
Author-email: your.email@example.com
Requires-Dist: pyperclip
